gwaportalpipeline/__init__.py
gwaportalpipeline/celery.py
gwaportalpipeline/common.py
gwaportalpipeline/enrichment.py
gwaportalpipeline/gwas.py
gwaportalpipeline/permute.py
gwaportalpipeline/rest.py
gwaportalpipeline/utils.py
gwaportalpipeline-0.2.11.dist-info/METADATA
gwaportalpipeline-0.2.11.dist-info/RECORD
gwaportalpipeline-0.2.11.dist-info/WHEEL
gwaportalpipeline-0.2.11.dist-info/pbr.json
gwaportalpipeline-0.2.11.dist-info/top_level.txt
